liexa_env/__init__.py
liexa_env/_env.py
liexa_env/tests/__init__.py
liexa_env/tests/test_autoload_functions.py
liexa_env/tests/test_export_and_print_functions.py
liexa_env/tests/test_getters_setters_casting_functions.py
liexa_env/tests/test_interpolation_functions.py
liexa_env/tests/test_json_yaml_import_functions.py
liexa_env/tests/test_load_functions.py
liexa_env/tests/test_parse_functions.py
liexa_env-0.0.10.dist-info/METADATA
liexa_env-0.0.10.dist-info/WHEEL
liexa_env-0.0.10.dist-info/top_level.txt
liexa_env-0.0.10.dist-info/RECORD
