Metadata-Version: 2.1
Name: liexa-env
Version: 0.0.10
Summary: A Python package for environment management.
Home-page: https://github.com/lifedrivendev/liexa-env
Author: lifedrivendev
Author-email: lifedrivendeveloper@gmail.com
Classifier: Programming Language :: Python :: 3
Classifier: License :: OSI Approved :: MIT License
Classifier: Operating System :: OS Independent
Requires-Python: >=3.12
